appai/__init__.py
appai/__main__.py
appai/agents/__init__.py
appai/agents/agent_pool.py
appai/agents/capabilities.py
appai/cache/__init__.py
appai/cache/manager.py
appai/cli/__init__.py
appai/cli/main.py
appai/core/__init__.py
appai/core/documentation.py
appai/core/task_decomposer.py
appai/db/__init__.py
appai/docs/__init__.py
appai/logging/__init__.py
appai/logging/agent_logger.py
appai/logging/log_manager.py
appai/logging/swarm_logger.py
appai/models/__init__.py
appai/models/agents.py
appai/models/communication.py
appai/models/config.py
appai/models/quality.py
appai/models/swarm.py
appai/models/tasks.py
appai/orchestration/__init__.py
appai/orchestration/execution_engine.py
appai/orchestration/swarm_coordinator.py
appai/orchestration/swarm_hub.py
appai/orchestration/task_broker.py
appai/prompts/__init__.py
appai/prompts/django.py
appai/prompts/registry.py
appai/tools/__init__.py
appai/tools/documentation_search.py
appai/tools/search_documentation.py
appai/utils/__init__.py
appai/utils/ai_code_extractor.py
appai/utils/exclusions.py
appai/utils/mcp_servers.py
appai/utils/quality_checker.py
appai-1.0.1.dist-info/METADATA
appai-1.0.1.dist-info/WHEEL
appai-1.0.1.dist-info/entry_points.txt
appai-1.0.1.dist-info/top_level.txt
appai-1.0.1.dist-info/RECORD
