Metadata-Version: 2.4
Name: appai
Version: 1.0.1
Summary: Swarm Intelligence System for Documentation-Driven Code Generation
Author: appai Team
License: MIT
Project-URL: Homepage, https://github.com/markolofsen/appai
Project-URL: Documentation, https://github.com/markolofsen/appai/tree/main/@dev
Project-URL: Repository, https://github.com/markolofsen/appai
Project-URL: Issues, https://github.com/markolofsen/appai/issues
Keywords: ai,swarm,code-generation,agents,llm
Classifier: Development Status :: 4 - Beta
Classifier: Intended Audience :: Developers
Classifier: License :: OSI Approved :: MIT License
Classifier: Programming Language :: Python :: 3
Classifier: Programming Language :: Python :: 3.10
Classifier: Programming Language :: Python :: 3.11
Classifier: Programming Language :: Python :: 3.12
Classifier: Topic :: Software Development :: Code Generators
Classifier: Topic :: Software Development :: Libraries :: Python Modules
Requires-Python: <3.13,>=3.12
Requires-Dist: agency-swarm>=1.0.2
Requires-Dist: pydantic>=2.0.0
Requires-Dist: openai>=1.0.0
Requires-Dist: click>=8.0.0
Requires-Dist: python-dotenv>=1.0.0
Requires-Dist: chromadb<2.0.0,>=1.1.0
Provides-Extra: vector
Requires-Dist: chromadb>=0.4.0; extra == "vector"
Provides-Extra: cache
Requires-Dist: redis>=5.0.0; extra == "cache"
Provides-Extra: all
Requires-Dist: chromadb>=0.4.0; extra == "all"
Requires-Dist: redis>=5.0.0; extra == "all"
Provides-Extra: dev
Requires-Dist: pytest>=7.0.0; extra == "dev"
Requires-Dist: pytest-asyncio>=0.21.0; extra == "dev"
Requires-Dist: pytest-cov>=4.0.0; extra == "dev"
Requires-Dist: black>=23.0.0; extra == "dev"
Requires-Dist: ruff>=0.1.0; extra == "dev"
Requires-Dist: mypy>=1.0.0; extra == "dev"
Provides-Extra: devops
Requires-Dist: rich>=13.0.0; extra == "devops"
Requires-Dist: questionary>=2.0.0; extra == "devops"
Requires-Dist: tomlkit>=0.12.0; extra == "devops"
Requires-Dist: build>=1.0.0; extra == "devops"
